totypes/__init__.py
totypes/json_utils.py
totypes/partition_utils.py
totypes/py.typed
totypes/symmetry.py
totypes/types.py
totypes-0.9.1.dist-info/licenses/LICENSE
totypes-0.9.1.dist-info/METADATA
totypes-0.9.1.dist-info/WHEEL
totypes-0.9.1.dist-info/top_level.txt
totypes-0.9.1.dist-info/RECORD
