Metadata-Version: 2.4
Name: totypes
Version: 0.9.1
Summary: Custom datatypes useful in a topology optimization context
Author-email: "Martin F. Schubert" <mfschubert@gmail.com>
Maintainer-email: "Martin F. Schubert" <mfschubert@gmail.com>
License-Expression: MIT
Keywords: topology,optimization,jax,inverse design
Requires-Python: >=3.7
License-File: LICENSE
Requires-Dist: jax
Requires-Dist: jaxlib
Requires-Dist: numpy
Provides-Extra: tests
Requires-Dist: optax; extra == "tests"
Requires-Dist: parameterized; extra == "tests"
Requires-Dist: pytest; extra == "tests"
Requires-Dist: pytest-cov; extra == "tests"
Requires-Dist: pytest-subtests; extra == "tests"
Provides-Extra: dev
Requires-Dist: bump-my-version; extra == "dev"
Requires-Dist: darglint; extra == "dev"
Requires-Dist: totypes[tests]; extra == "dev"
Requires-Dist: pre-commit; extra == "dev"
Dynamic: license-file
